{"type":"PR","pr":{"number":126,"head":"528fcacd5fd5be05c84de60542d16a103575eea8"},"user":"Brennan","status":"pending_review","branch":"cms/mobilize---episode-18---eve-proper-the-idc-explained","collection":"podcast","title":"Eve Proper: The IDC Explained","description":"Professor and activist Eve Proper talks about the role the Independent Democratic Conference plays in the New York State Legislature and why the upcoming Democratic primaries are so important. Time to dismantle the IDC (for real this time).","objects":{"entry":{"path":"src/pages/podcast/mobilize---episode-18---eve-proper-the-idc-explained.md","sha":"def21b4af0b8fd7ef638942dcdc4899fe93ab521"},"files":[]},"timeStamp":"2019-05-03T17:59:03.817Z"}